[
    {
        "id": "623dca3f0ad2ed52ac5d1b08",
        "picture": "http://placehold.it/32x32",
        "price": 67,
        "name": "Naomi Salazar"
    },
    {
        "id": "623dca3f162b9286b901e059",
        "picture": "http://placehold.it/32x32",
        "price": 316,
        "name": "Holland Brooks"
    },
    {
        "id": "623dca3fa4fd5ba356e99a63",
        "picture": "http://placehold.it/32x32",
        "price": 321,
        "name": "Powers Davenport"
    },
    {
        "id": "623dca3ff5f8d6957dfdc3c4",
        "picture": "http://placehold.it/32x32",
        "price": 271,
        "name": "Lucia Olsen"
    },
    {
        "id": "623dca3fea1cbb35e3aba8c6",
        "picture": "http://placehold.it/32x32",
        "price": 238,
        "name": "Bowman Watson"
    },
    {
        "id": "623dca3feaa3a73b43b9d8d3",
        "picture": "http://placehold.it/32x32",
        "price": 130,
        "name": "Barrera Powers"
    },
    {
        "id": "623dca3feaa3a73b43b9d8i3",
        "picture": "http://placehold.it/32x32",
        "price": 130,
        "name": "Barrera Powers"
    },
    {
        "id": "623dca3feaa3a73b43b9d8k3",
        "picture": "http://placehold.it/32x32",
        "price": 130,
        "name": "Barrera Powers"
    },
    {
        "id": "623dca3feaa3a73b43b9d8s3",
        "picture": "http://placehold.it/32x32",
        "price": 130,
        "name": "Barrera Powers"
    },
    {
        "id": "623dca3feaa3a73b43b9d8c3",
        "picture": "http://placehold.it/32x32",
        "price": 130,
        "name": "Barrera Powers"
    },
    {
        "id": "623dca3feaa3a73b43b9d8z3",
        "picture": "http://placehold.it/32x32",
        "price": 130,
        "name": "Barrera Powers"
    },
    {
        "id": "623dca3f01e290e380e0b809",
        "picture": "http://placehold.it/32x32",
        "price": 269,
        "name": "Olson Rowe"
    }
]